videoCrawler/__init__.py
videoCrawler/videoCrawler.py
videoCrawler-0.0.1.dist-info/METADATA
videoCrawler-0.0.1.dist-info/RECORD
videoCrawler-0.0.1.dist-info/WHEEL
videoCrawler-0.0.1.dist-info/top_level.txt
